README.rst
setup.py
django_event_logger.egg-info/PKG-INFO
django_event_logger.egg-info/SOURCES.txt
django_event_logger.egg-info/dependency_links.txt
django_event_logger.egg-info/requires.txt
django_event_logger.egg-info/top_level.txt
django_events/EventLogger.py
django_events/__init__.py
django_events/admin.py
django_events/models.py
django_events/tests.py
django_events/migrations/0001_initial.py
django_events/migrations/0002_auto_20151017_1723.py
django_events/migrations/__init__.py