Metadata-Version: 1.1
Name: django-event-logger
Version: 0.8.21
Summary: An easy-to-use event logger for Django.
Home-page: https://github.com/brandonberney/django-event-logger/
Author: Brandon B.
Author-email: unaffiliate@outlook.com
License: UNKNOWN
Download-URL: https://github.com/brandonberney/django-event-logger/tarball/v0.8.21
Keywords: django,events,logger,logging
Platform: UNKNOWN
